ascii_art/lib/cat_dad.txt
ascii_art/lib/musical_note.txt
ascii_art/lib/tv.txt
ascii_art/main.py
ascii_art/toolchain/option_utils.py
sleepys_ascii_art_printer-0.1.1.dist-info/LICENSE
sleepys_ascii_art_printer-0.1.1.dist-info/WHEEL
sleepys_ascii_art_printer-0.1.1.dist-info/METADATA
sleepys_ascii_art_printer-0.1.1.dist-info/RECORD
