Metadata-Version: 2.1
Name: sleepys-ascii-art-printer
Version: 0.1.1
Summary: An ascii art library and output tool for the command line.
Home-page: https://github.com/anthonybench/ASCII_art
License: GNU GPL
Keywords: ascii,art,cli
Author: anthonybench
Author-email: anthonybenchyep@gmail.com
Requires-Python: >=3.10,<4.0
Classifier: License :: Other/Proprietary License
Classifier: Programming Language :: Python :: 3
Classifier: Programming Language :: Python :: 3.10
Project-URL: Repository, https://github.com/anthonybench/ASCII_art
